{"code":"200550","name":"江铃B","industry":"汽车","industries":["汽车","商用车","商用载货车"],"periods":{"2025-06-30":{"mv":15484368,"num":1510670,"ratio":0.175,"holders":[{"holder":"全国社保基金一一七组合","group":"社保基金","num":1510670.0,"ratio":0.175,"mv":15484367.5,"change":"新进"}]},"2026-03-31":{"mv":28990500,"num":2887500,"ratio":0.3345,"holders":[{"holder":"招商基金管理有限公司-社保基金1903组合","group":"社保基金","num":2887500.0,"ratio":0.3345,"mv":28990500.0,"change":"新进"}]},"2016-03-31":{"mv":672281345,"num":29932384,"ratio":3.4675,"holders":[{"holder":"中国证券金融股份有限公司","group":"证金公司","num":22745784.0,"ratio":2.635,"mv":510870308.64,"change":"不变"},{"holder":"中央汇金资产管理有限公司","group":"汇金资管","num":7186600.0,"ratio":0.8325,"mv":161411036.0,"change":"不变"}]},"2016-06-30":{"mv":143157072,"num":7186600,"ratio":0.8325,"holders":[{"holder":"中央汇金资产管理有限责任公司","group":"汇金资管","num":7186600.0,"ratio":0.8325,"mv":143157072.0,"change":"不变"}]},"2016-09-30":{"mv":592062556,"num":29932384,"ratio":3.4675,"holders":[{"holder":"中国证券金融股份有限公司","group":"证金公司","num":22745784.0,"ratio":2.635,"mv":449911607.52,"change":"新进"},{"holder":"中央汇金资产管理有限责任公司","group":"汇金资管","num":7186600.0,"ratio":0.8325,"mv":142150948.0,"change":"不变"}]},"2016-12-31":{"mv":575300420,"num":29932384,"ratio":3.4675,"holders":[{"holder":"中国证券金融股份有限公司","group":"证金公司","num":22745784.0,"ratio":2.635,"mv":437173968.48,"change":"不变"},{"holder":"中央汇金资产管理有限责任公司","group":"汇金资管","num":7186600.0,"ratio":0.8325,"mv":138126452.0,"change":"不变"}]},"2017-03-31":{"mv":555204913,"num":29930184,"ratio":3.4673,"holders":[{"holder":"中国证券金融股份有限公司","group":"证金公司","num":22743584.0,"ratio":2.6348,"mv":421893483.2,"change":"-2200"},{"holder":"中央汇金资产管理有限责任公司","group":"汇金资管","num":7186600.0,"ratio":0.8325,"mv":133311430.0,"change":"不变"}]},"2017-06-30":{"mv":491453621,"num":29930184,"ratio":3.4673,"holders":[{"holder":"中国证券金融股份有限公司","group":"证金公司","num":22743584.0,"ratio":2.6348,"mv":373449649.28,"change":"不变"},{"holder":"中央汇金资产管理有限责任公司","group":"汇金资管","num":7186600.0,"ratio":0.8325,"mv":118003972.0,"change":"不变"}]},"2017-09-30":{"mv":477386435,"num":29930184,"ratio":3.4673,"holders":[{"holder":"中国证券金融股份有限公司","group":"证金公司","num":22743584.0,"ratio":2.6348,"mv":362760164.8,"change":"不变"},{"holder":"中央汇金资产管理有限责任公司","group":"汇金资管","num":7186600.0,"ratio":0.8325,"mv":114626270.0,"change":"不变"}]},"2017-12-31":{"mv":382507752,"num":29930184,"ratio":3.4673,"holders":[{"holder":"中国证券金融股份有限公司","group":"证金公司","num":22743584.0,"ratio":2.6348,"mv":290663003.52,"change":"不变"},{"holder":"中央汇金资产管理有限责任公司","group":"汇金资管","num":7186600.0,"ratio":0.8325,"mv":91844748.0,"change":"不变"}]},"2018-03-31":{"mv":359162208,"num":29930184,"ratio":3.4673,"holders":[{"holder":"中国证券金融股份有限公司","group":"证金公司","num":22743584.0,"ratio":2.6348,"mv":272923008.0,"change":"不变"},{"holder":"中央汇金资产管理有限责任公司","group":"汇金资管","num":7186600.0,"ratio":0.8325,"mv":86239200.0,"change":"不变"}]},"2018-06-30":{"mv":297805331,"num":29930184,"ratio":3.4673,"holders":[{"holder":"中国证券金融股份有限公司","group":"证金公司","num":22743584.0,"ratio":2.6348,"mv":226298660.8,"change":"不变"},{"holder":"中央汇金资产管理有限责任公司","group":"汇金资管","num":7186600.0,"ratio":0.8325,"mv":71506670.0,"change":"不变"}]},"2018-09-30":{"mv":253124941,"num":30644666,"ratio":3.55,"holders":[{"holder":"中国证券金融股份有限公司","group":"证金公司","num":23458066.0,"ratio":2.7175,"mv":193763625.16,"change":"714482"},{"holder":"中央汇金资产管理有限责任公司","group":"汇金资管","num":7186600.0,"ratio":0.8325,"mv":59361316.0,"change":"不变"}]},"2018-12-31":{"mv":240560628,"num":30644666,"ratio":3.55,"holders":[{"holder":"中国证券金融股份有限公司","group":"证金公司","num":23458066.0,"ratio":2.7175,"mv":184145818.1,"change":"不变"},{"holder":"中央汇金资产管理有限责任公司","group":"汇金资管","num":7186600.0,"ratio":0.8325,"mv":56414810.0,"change":"不变"}]},"2019-03-31":{"mv":361309247,"num":37133530,"ratio":4.3017,"holders":[{"holder":"中国证券金融股份有限公司","group":"证金公司","num":23458066.0,"ratio":2.7175,"mv":228246982.18,"change":"不变"},{"holder":"中央汇金资产管理有限责任公司","group":"汇金资管","num":7186600.0,"ratio":0.8325,"mv":69925618.0,"change":"不变"},{"holder":"全国社保基金六零二组合","group":"社保基金","num":6488864.0,"ratio":0.7517,"mv":63136646.72,"change":"新进"}]},"2019-06-30":{"mv":260239627,"num":35895121,"ratio":4.1582,"holders":[{"holder":"中国证券金融股份有限公司","group":"证金公司","num":23458066.0,"ratio":2.7175,"mv":170070978.5,"change":"不变"},{"holder":"中央汇金资产管理有限责任公司","group":"汇金资管","num":7186600.0,"ratio":0.8325,"mv":52102850.0,"change":"不变"},{"holder":"全国社保基金五零四组合","group":"社保基金","num":5250455.0,"ratio":0.6082,"mv":38065798.75,"change":"新进"}]},"2019-09-30":{"mv":302292357,"num":43747085,"ratio":5.0678,"holders":[{"holder":"中国证券金融股份有限公司","group":"证金公司","num":23458066.0,"ratio":2.7175,"mv":162095236.06,"change":"不变"},{"holder":"全国社保基金六零二组合","group":"社保基金","num":7851964.0,"ratio":0.9096,"mv":54257071.24,"change":"新进"},{"holder":"中央汇金资产管理有限责任公司","group":"汇金资管","num":7186600.0,"ratio":0.8325,"mv":49659406.0,"change":"不变"},{"holder":"全国社保基金五零四组合","group":"社保基金","num":5250455.0,"ratio":0.6082,"mv":36280644.05,"change":"不变"}]},"2019-12-31":{"mv":211148597,"num":35132878,"ratio":4.0699,"holders":[{"holder":"中国证券金融股份有限公司","group":"证金公司","num":23458066.0,"ratio":2.7175,"mv":140982976.66,"change":"不变"},{"holder":"中央汇金资产管理有限责任公司","group":"汇金资管","num":7186600.0,"ratio":0.8325,"mv":43191466.0,"change":"不变"},{"holder":"全国社保基金六零二组合","group":"社保基金","num":4488212.0,"ratio":0.5199,"mv":26974154.12,"change":"-3363752"}]},"2020-03-31":{"mv":136981657,"num":30644666,"ratio":3.55,"holders":[{"holder":"中国证券金融股份有限公司","group":"证金公司","num":23458066.0,"ratio":2.7175,"mv":104857555.02,"change":"不变"},{"holder":"中央汇金资产管理有限责任公司","group":"汇金资管","num":7186600.0,"ratio":0.8325,"mv":32124102.0,"change":"不变"}]},"2020-06-30":{"mv":152303990,"num":30644666,"ratio":3.55,"holders":[{"holder":"中国证券金融股份有限公司","group":"证金公司","num":23458066.0,"ratio":2.7175,"mv":116586588.02,"change":"不变"},{"holder":"中央汇金资产管理有限责任公司","group":"汇金资管","num":7186600.0,"ratio":0.8325,"mv":35717402.0,"change":"不变"}]},"2020-09-30":{"mv":182335763,"num":30644666,"ratio":3.55,"holders":[{"holder":"中国证券金融股份有限公司","group":"证金公司","num":23458066.0,"ratio":2.7175,"mv":139575492.7,"change":"不变"},{"holder":"中央汇金资产管理有限责任公司","group":"汇金资管","num":7186600.0,"ratio":0.8325,"mv":42760270.0,"change":"不变"}]},"2020-12-31":{"mv":200880153,"num":27293499,"ratio":3.1618,"holders":[{"holder":"中国证券金融股份有限公司","group":"证金公司","num":20106899.0,"ratio":2.3293,"mv":147986776.64,"change":"-3351167"},{"holder":"中央汇金资产管理有限责任公司","group":"汇金资管","num":7186600.0,"ratio":0.8325,"mv":52893376.0,"change":"不变"}]},"2021-03-31":{"mv":185327550,"num":18312999,"ratio":2.1215,"holders":[{"holder":"中国证券金融股份有限公司","group":"证金公司","num":13669498.0,"ratio":1.5836,"mv":138335319.76,"change":"-6437401"},{"holder":"全国社保基金一一八组合","group":"社保基金","num":4643501.0,"ratio":0.5379,"mv":46992230.12,"change":"新进"}]},"2021-06-30":{"mv":88649442,"num":7007861,"ratio":0.8118,"holders":[{"holder":"全国社保基金一一八组合","group":"社保基金","num":4643501.0,"ratio":0.5379,"mv":58740287.65,"change":"不变"},{"holder":"中国证券金融股份有限公司","group":"证金公司","num":2364360.0,"ratio":0.2739,"mv":29909154.0,"change":"-11305138"}]},"2021-09-30":{"mv":56136618,"num":7105901,"ratio":0.8232,"holders":[{"holder":"全国社保基金一一八组合","group":"社保基金","num":4643501.0,"ratio":0.5379,"mv":36683657.9,"change":"不变"},{"holder":"全国社保基金四一二组合","group":"社保基金","num":2462400.0,"ratio":0.2853,"mv":19452960.0,"change":"新进"}]},"2021-12-31":{"mv":50755889,"num":6643441,"ratio":0.7696,"holders":[{"holder":"全国社保基金一一八组合","group":"社保基金","num":6643441.0,"ratio":0.7696,"mv":50755889.24,"change":"1999940"}]},"2022-03-31":{"mv":40393212,"num":6743441,"ratio":0.7812,"holders":[{"holder":"全国社保基金一一八组合","group":"社保基金","num":6743441.0,"ratio":0.7812,"mv":40393211.59,"change":"100000"}]},"2022-06-30":{"mv":50852597,"num":7152264,"ratio":0.8285,"holders":[{"holder":"全国社保基金一一八组合","group":"社保基金","num":3989977.0,"ratio":0.4622,"mv":28368736.47,"change":"-2753464"},{"holder":"社保基金1103组合","group":"社保基金","num":3162287.0,"ratio":0.3663,"mv":22483860.57,"change":"新进"}]},"2022-09-30":{"mv":25797179,"num":3844587,"ratio":0.4454,"holders":[{"holder":"社保基金1103组合","group":"社保基金","num":3844587.0,"ratio":0.4454,"mv":25797178.77,"change":"682300"}]}}}