{"code":"300136","name":"信维通信","industry":"电子","industries":["电子","消费电子","消费电子零部件及组装"],"periods":{"2024-03-31":{"mv":665280000,"num":33000000,"ratio":3.4106,"holders":[{"holder":"全国社保基金一零三组合","group":"社保基金","num":33000000.0,"ratio":3.4106,"mv":665280000.0,"change":"74200"}]},"2024-06-30":{"mv":646140000,"num":33000000,"ratio":3.4106,"holders":[{"holder":"全国社保基金一零三组合","group":"社保基金","num":33000000.0,"ratio":3.4106,"mv":646140000.0,"change":"不变"}]},"2024-09-30":{"mv":788800000,"num":34000000,"ratio":3.514,"holders":[{"holder":"全国社保基金一零三组合","group":"社保基金","num":34000000.0,"ratio":3.514,"mv":788800000.0,"change":"不变"}]},"2024-12-31":{"mv":941280000,"num":37000000,"ratio":3.824,"holders":[{"holder":"全国社保基金一零三组合","group":"社保基金","num":37000000.0,"ratio":3.824,"mv":941280000.0,"change":"3000000"}]},"2025-03-31":{"mv":879120000,"num":37000000,"ratio":3.824,"holders":[{"holder":"全国社保基金一零三组合","group":"社保基金","num":37000000.0,"ratio":3.824,"mv":879120000.0,"change":"不变"}]},"2025-06-30":{"mv":828800000,"num":37000000,"ratio":3.824,"holders":[{"holder":"全国社保基金一零三组合","group":"社保基金","num":37000000.0,"ratio":3.824,"mv":828800000.0,"change":"不变"}]},"2025-09-30":{"mv":980400000,"num":38000000,"ratio":3.9274,"holders":[{"holder":"全国社保基金一零三组合","group":"社保基金","num":38000000.0,"ratio":3.9274,"mv":980400000.0,"change":"1000000"}]},"2025-12-31":{"mv":2479559800,"num":39992900,"ratio":4.1334,"holders":[{"holder":"全国社保基金一零三组合","group":"社保基金","num":30992900.0,"ratio":3.2032,"mv":1921559800.0,"change":"-7007100"},{"holder":"全国社保基金五零三组合","group":"社保基金","num":9000000.0,"ratio":0.9302,"mv":558000000.0,"change":"新进"}]},"2026-03-31":{"mv":1494080000,"num":23000000,"ratio":2.3771,"holders":[{"holder":"全国社保基金一零三组合","group":"社保基金","num":23000000.0,"ratio":2.3771,"mv":1494080000.0,"change":"-7992900"}]},"2016-03-31":{"mv":661738112,"num":22439407,"ratio":3.75,"holders":[{"holder":"全国社保基金一零八组合","group":"社保基金","num":15439418.0,"ratio":2.5802,"mv":455308436.82,"change":"6499358"},{"holder":"全国社保基金四一三组合","group":"社保基金","num":6999989.0,"ratio":1.1698,"mv":206429675.61,"change":"新进"}]},"2016-06-30":{"mv":769296662,"num":36703085,"ratio":3.8336,"holders":[{"holder":"全国社保基金一零八组合","group":"社保基金","num":24703069.0,"ratio":2.5802,"mv":517776326.24,"change":"9263651"},{"holder":"全国社保基金四一三组合","group":"社保基金","num":12000016.0,"ratio":1.2534,"mv":251520335.36,"change":"5000027"}]},"2016-09-30":{"mv":554080705,"num":21703122,"ratio":2.2669,"holders":[{"holder":"全国社保基金一零八组合","group":"社保基金","num":21703122.0,"ratio":2.2669,"mv":554080704.66,"change":"-2999947"}]},"2016-12-31":{"mv":741088036,"num":26003089,"ratio":2.7063,"holders":[{"holder":"全国社保基金一零八组合","group":"社保基金","num":26003089.0,"ratio":2.7063,"mv":741088036.5,"change":"4299967"}]},"2017-03-31":{"mv":955033359,"num":27803009,"ratio":2.8348,"holders":[{"holder":"全国社保基金一零八组合","group":"社保基金","num":27803009.0,"ratio":2.8348,"mv":955033359.15,"change":"1799920"}]},"2017-06-30":{"mv":1084662420,"num":27103009,"ratio":2.7576,"holders":[{"holder":"全国社保基金一零八组合","group":"社保基金","num":27103009.0,"ratio":2.7576,"mv":1084662420.18,"change":"-700000"}]},"2017-09-30":{"mv":1009899492,"num":24045226,"ratio":2.4465,"holders":[{"holder":"全国社保基金一零八组合","group":"社保基金","num":24045226.0,"ratio":2.4465,"mv":1009899492.0,"change":"-3057783"}]},"2017-12-31":{"mv":1219092958,"num":24045226,"ratio":2.4465,"holders":[{"holder":"全国社保基金一零八组合","group":"社保基金","num":24045226.0,"ratio":2.4465,"mv":1219092958.2,"change":"不变"}]},"2018-03-31":{"mv":822507382,"num":22045226,"ratio":2.243,"holders":[{"holder":"全国社保基金一零八组合","group":"社保基金","num":22045226.0,"ratio":2.243,"mv":822507382.06,"change":"-2000000"}]},"2018-06-30":{"mv":722037427,"num":23496174,"ratio":2.3907,"holders":[{"holder":"全国社保基金一零八组合","group":"社保基金","num":23496174.0,"ratio":2.3907,"mv":722037427.02,"change":"1450948"}]},"2018-09-30":{"mv":852801226,"num":32000046,"ratio":3.2801,"holders":[{"holder":"全国社保基金一零八组合","group":"社保基金","num":32000046.0,"ratio":3.2801,"mv":852801225.9,"change":"8503872"}]},"2018-12-31":{"mv":594275994,"num":27500046,"ratio":2.8188,"holders":[{"holder":"全国社保基金一零八组合","group":"社保基金","num":27500046.0,"ratio":2.8188,"mv":594275994.06,"change":"-4500000"}]},"2019-09-30":{"mv":590389614,"num":16491330,"ratio":1.7026,"holders":[{"holder":"全国社保基金一一三组合","group":"社保基金","num":9133858.0,"ratio":0.943,"mv":326992116.4,"change":"新进"},{"holder":"基本养老保险基金八零二组合","group":"养老基金","num":7357472.0,"ratio":0.7596,"mv":263397497.6,"change":"新进"}]},"2019-12-31":{"mv":349216844,"num":7695391,"ratio":0.7945,"holders":[{"holder":"全国社保基金一零一组合","group":"社保基金","num":7695391.0,"ratio":0.7945,"mv":349216843.58,"change":"新进"}]},"2020-03-31":{"mv":329209418,"num":9592349,"ratio":0.9903,"holders":[{"holder":"全国社保基金一零一组合","group":"社保基金","num":9592349.0,"ratio":0.9903,"mv":329209417.68,"change":"1896958"}]},"2020-09-30":{"mv":1266773916,"num":23239294,"ratio":2.4135,"holders":[{"holder":"全国社保基金一零三组合","group":"社保基金","num":23239294.0,"ratio":2.4135,"mv":1266773915.94,"change":"新进"}]},"2020-12-31":{"mv":1058422900,"num":29498966,"ratio":3.0488,"holders":[{"holder":"全国社保基金一零三组合","group":"社保基金","num":29498966.0,"ratio":3.0488,"mv":1058422900.08,"change":"6259672"}]},"2021-03-31":{"mv":837475645,"num":29498966,"ratio":3.0488,"holders":[{"holder":"全国社保基金一零三组合","group":"社保基金","num":29498966.0,"ratio":3.0488,"mv":837475644.74,"change":"不变"}]},"2021-06-30":{"mv":910928070,"num":29498966,"ratio":3.0488,"holders":[{"holder":"全国社保基金一零三组合","group":"社保基金","num":29498966.0,"ratio":3.0488,"mv":910928070.08,"change":"不变"}]},"2021-09-30":{"mv":608580000,"num":27000000,"ratio":2.7905,"holders":[{"holder":"全国社保基金一零三组合","group":"社保基金","num":27000000.0,"ratio":2.7905,"mv":608580000.0,"change":"-2498966"}]},"2021-12-31":{"mv":670978050,"num":26499923,"ratio":2.7388,"holders":[{"holder":"全国社保基金一零三组合","group":"社保基金","num":26499923.0,"ratio":2.7388,"mv":670978050.36,"change":"-500077"}]},"2022-03-31":{"mv":486808612,"num":26999923,"ratio":2.7905,"holders":[{"holder":"全国社保基金一零三组合","group":"社保基金","num":26999923.0,"ratio":2.7905,"mv":486808611.69,"change":"500000"}]},"2022-06-30":{"mv":454948703,"num":26999923,"ratio":2.7905,"holders":[{"holder":"全国社保基金一零三组合","group":"社保基金","num":26999923.0,"ratio":2.7905,"mv":454948702.55,"change":"不变"}]},"2022-09-30":{"mv":382048910,"num":26999923,"ratio":2.7905,"holders":[{"holder":"全国社保基金一零三组合","group":"社保基金","num":26999923.0,"ratio":2.7905,"mv":382048910.45,"change":"不变"}]},"2022-12-31":{"mv":487208829,"num":29509923,"ratio":3.0499,"holders":[{"holder":"全国社保基金一零三组合","group":"社保基金","num":29509923.0,"ratio":3.0499,"mv":487208828.73,"change":"2510000"}]},"2023-03-31":{"mv":617347589,"num":29509923,"ratio":3.0499,"holders":[{"holder":"全国社保基金一零三组合","group":"社保基金","num":29509923.0,"ratio":3.0499,"mv":617347589.16,"change":"不变"}]},"2023-06-30":{"mv":592360000,"num":29500000,"ratio":3.0489,"holders":[{"holder":"全国社保基金一零三组合","group":"社保基金","num":29500000.0,"ratio":3.0489,"mv":592360000.0,"change":"-9923"}]},"2023-09-30":{"mv":582920000,"num":29500000,"ratio":3.0489,"holders":[{"holder":"全国社保基金一零三组合","group":"社保基金","num":29500000.0,"ratio":3.0489,"mv":582920000.0,"change":"不变"}]},"2023-12-31":{"mv":777048880,"num":32925800,"ratio":3.4029,"holders":[{"holder":"全国社保基金一零三组合","group":"社保基金","num":32925800.0,"ratio":3.4029,"mv":777048880.0,"change":"3425800"}]}}}