{"code":"400272","name":"鹏博士3","industry":"其他","industries":["其他"],"periods":{"2016-03-31":{"mv":0,"num":22634970,"ratio":1.6163,"holders":[{"holder":"中国证券金融股份有限公司","group":"证金公司","num":22634970.0,"ratio":1.6163,"mv":0.0,"change":"新进"}]},"2016-06-30":{"mv":0,"num":19877338,"ratio":1.4062,"holders":[{"holder":"中国证券金融股份有限公司","group":"证金公司","num":19877338.0,"ratio":1.4062,"mv":0.0,"change":"-2757632"}]},"2017-12-31":{"mv":0,"num":70187404,"ratio":4.8998,"holders":[{"holder":"中国证券金融股份有限公司","group":"证金公司","num":70187404.0,"ratio":4.8998,"mv":0.0,"change":"新进"}]},"2018-03-31":{"mv":0,"num":70187404,"ratio":4.8998,"holders":[{"holder":"中国证券金融股份有限公司","group":"证金公司","num":70187404.0,"ratio":4.8998,"mv":0.0,"change":"不变"}]},"2018-06-30":{"mv":0,"num":70187404,"ratio":4.8998,"holders":[{"holder":"中国证券金融股份有限公司","group":"证金公司","num":70187404.0,"ratio":4.8998,"mv":0.0,"change":"不变"}]},"2018-09-30":{"mv":0,"num":70190842,"ratio":4.9,"holders":[{"holder":"中国证券金融股份有限公司","group":"证金公司","num":70190842.0,"ratio":4.9,"mv":0.0,"change":"3438"}]},"2018-12-31":{"mv":0,"num":70190842,"ratio":4.9,"holders":[{"holder":"中国证券金融股份有限公司","group":"证金公司","num":70190842.0,"ratio":4.9,"mv":0.0,"change":"不变"}]},"2019-03-31":{"mv":0,"num":70190842,"ratio":4.9,"holders":[{"holder":"中国证券金融股份有限公司","group":"证金公司","num":70190842.0,"ratio":4.9,"mv":0.0,"change":"不变"}]},"2019-06-30":{"mv":0,"num":70190842,"ratio":4.9,"holders":[{"holder":"中国证券金融股份有限公司","group":"证金公司","num":70190842.0,"ratio":4.9,"mv":0.0,"change":"不变"}]},"2019-09-30":{"mv":0,"num":70190842,"ratio":4.9002,"holders":[{"holder":"中国证券金融股份有限公司","group":"证金公司","num":70190842.0,"ratio":4.9002,"mv":0.0,"change":"不变"}]},"2019-12-31":{"mv":0,"num":70190842,"ratio":4.9002,"holders":[{"holder":"中国证券金融股份有限公司","group":"证金公司","num":70190842.0,"ratio":4.9002,"mv":0.0,"change":"不变"}]},"2020-03-31":{"mv":0,"num":70190842,"ratio":4.9002,"holders":[{"holder":"中国证券金融股份有限公司","group":"证金公司","num":70190842.0,"ratio":4.9002,"mv":0.0,"change":"不变"}]},"2020-06-30":{"mv":0,"num":70190842,"ratio":4.9002,"holders":[{"holder":"中国证券金融股份有限公司","group":"证金公司","num":70190842.0,"ratio":4.9002,"mv":0.0,"change":"不变"}]},"2020-09-30":{"mv":0,"num":70190842,"ratio":4.9002,"holders":[{"holder":"中国证券金融股份有限公司","group":"证金公司","num":70190842.0,"ratio":4.9002,"mv":0.0,"change":"不变"}]},"2020-12-31":{"mv":0,"num":64142342,"ratio":4.478,"holders":[{"holder":"中国证券金融股份有限公司","group":"证金公司","num":64142342.0,"ratio":4.478,"mv":0.0,"change":"-6048500"}]}}}