{"code":"600025","name":"华能水电","industry":"公用事业","industries":["公用事业","电力","水力发电"],"periods":{"2019-03-31":{"mv":53535750,"num":13057500,"ratio":0.0725,"holders":[{"holder":"全国社保基金四一二组合","group":"社保基金","num":13057500.0,"ratio":0.0725,"mv":53535750.0,"change":"新进"}]},"2019-09-30":{"mv":219517329,"num":51772955,"ratio":0.2876,"holders":[{"holder":"全国社保基金一零五组合","group":"社保基金","num":33936500.0,"ratio":0.1885,"mv":143890760.0,"change":"新进"},{"holder":"全国社保基金六零三组合","group":"社保基金","num":17836455.0,"ratio":0.0991,"mv":75626569.2,"change":"新进"}]},"2019-12-31":{"mv":57354780,"num":13591180,"ratio":0.0755,"holders":[{"holder":"全国社保基金四零七组合","group":"社保基金","num":13591180.0,"ratio":0.0755,"mv":57354779.6,"change":"新进"}]},"2022-03-31":{"mv":160049732,"num":27499954,"ratio":0.1528,"holders":[{"holder":"全国社保基金一零八组合","group":"社保基金","num":27499954.0,"ratio":0.1528,"mv":160049732.28,"change":"新进"}]}}}