{"code":"600864","name":"哈投股份","industry":"非银金融","industries":["非银金融","证券Ⅱ","证券Ⅲ"],"periods":{"2016-03-31":{"mv":732414292,"num":57130600,"ratio":10.4559,"holders":[{"holder":"中央汇金资产管理有限责任公司","group":"汇金资管","num":14740600.0,"ratio":2.6979,"mv":188974492.0,"change":"不变"},{"holder":"大成基金-农业银行-大成中证金融资产管理计划","group":"证金公司","num":4239000.0,"ratio":0.7758,"mv":54343980.0,"change":"不变"},{"holder":"工银瑞信基金-农业银行-工银瑞信中证金融资产管理计划","group":"证金公司","num":4239000.0,"ratio":0.7758,"mv":54343980.0,"change":"不变"},{"holder":"中欧基金-农业银行-中欧中证金融资产管理计划","group":"证金公司","num":4239000.0,"ratio":0.7758,"mv":54343980.0,"change":"不变"},{"holder":"南方基金-农业银行-南方中证金融资产管理计划","group":"证金公司","num":4239000.0,"ratio":0.7758,"mv":54343980.0,"change":"不变"},{"holder":"广发基金-农业银行-广发中证金融资产管理计划","group":"证金公司","num":4239000.0,"ratio":0.7758,"mv":54343980.0,"change":"不变"},{"holder":"嘉实基金-农业银行-嘉实中证金融资产管理计划","group":"证金公司","num":4239000.0,"ratio":0.7758,"mv":54343980.0,"change":"不变"},{"holder":"华夏基金-农业银行-华夏中证金融资产管理计划","group":"证金公司","num":4239000.0,"ratio":0.7758,"mv":54343980.0,"change":"不变"},{"holder":"银华基金-农业银行-银华中证金融资产管理计划","group":"证金公司","num":4239000.0,"ratio":0.7758,"mv":54343980.0,"change":"不变"},{"holder":"易方达基金-农业银行-易方达中证金融资产管理计划","group":"证金公司","num":4239000.0,"ratio":0.7758,"mv":54343980.0,"change":"不变"},{"holder":"博时基金-农业银行-博时中证金融资产管理计划","group":"证金公司","num":4239000.0,"ratio":0.7758,"mv":54343980.0,"change":"不变"}]},"2016-06-30":{"mv":249193397,"num":22189973,"ratio":4.0613,"holders":[{"holder":"中央汇金资产管理有限责任公司","group":"汇金资管","num":14740600.0,"ratio":2.6979,"mv":165536938.0,"change":"不变"},{"holder":"广发基金-农业银行-广发中证金融资产管理计划","group":"证金公司","num":2738700.0,"ratio":0.5012,"mv":30755601.0,"change":"-1500300"},{"holder":"中国证券金融股份有限公司","group":"证金公司","num":2402973.0,"ratio":0.4398,"mv":26985386.79,"change":"新进"},{"holder":"华夏基金-农业银行-华夏中证金融资产管理计划","group":"证金公司","num":2307700.0,"ratio":0.4224,"mv":25915471.0,"change":"-1931300"}]},"2016-09-30":{"mv":248083898,"num":22189973,"ratio":1.0524,"holders":[{"holder":"中央汇金资产管理有限责任公司","group":"汇金资管","num":14740600.0,"ratio":0.6991,"mv":164799908.0,"change":"不变"},{"holder":"广发基金-农业银行-广发中证金融资产管理计划","group":"证金公司","num":2738700.0,"ratio":0.1299,"mv":30618666.0,"change":"不变"},{"holder":"中国证券金融股份有限公司","group":"证金公司","num":2402973.0,"ratio":0.114,"mv":26865238.14,"change":"不变"},{"holder":"华夏基金-农业银行-华夏中证金融资产管理计划","group":"证金公司","num":2307700.0,"ratio":0.1094,"mv":25800086.0,"change":"不变"}]},"2016-12-31":{"mv":272350704,"num":23848573,"ratio":1.1311,"holders":[{"holder":"中央汇金资产管理有限责任公司","group":"汇金资管","num":14740600.0,"ratio":0.6991,"mv":168337652.0,"change":"不变"},{"holder":"广发基金-农业银行-广发中证金融资产管理计划","group":"证金公司","num":2738700.0,"ratio":0.1299,"mv":31275954.0,"change":"不变"},{"holder":"中国证券金融股份有限公司","group":"证金公司","num":2402973.0,"ratio":0.114,"mv":27441951.66,"change":"不变"},{"holder":"华夏基金-农业银行-华夏中证金融资产管理计划","group":"证金公司","num":2307700.0,"ratio":0.1094,"mv":26353934.0,"change":"不变"},{"holder":"嘉实基金-农业银行-嘉实中证金融资产管理计划","group":"证金公司","num":1658600.0,"ratio":0.0787,"mv":18941212.0,"change":"新进"}]},"2017-03-31":{"mv":240155130,"num":23848573,"ratio":1.1311,"holders":[{"holder":"中央汇金资产管理有限责任公司","group":"汇金资管","num":14740600.0,"ratio":0.6991,"mv":148437842.0,"change":"不变"},{"holder":"广发基金-农业银行-广发中证金融资产管理计划","group":"证金公司","num":2738700.0,"ratio":0.1299,"mv":27578709.0,"change":"不变"},{"holder":"中国证券金融股份有限公司","group":"证金公司","num":2402973.0,"ratio":0.114,"mv":24197938.11,"change":"不变"},{"holder":"华夏基金-农业银行-华夏中证金融资产管理计划","group":"证金公司","num":2307700.0,"ratio":0.1094,"mv":23238539.0,"change":"不变"},{"holder":"嘉实基金-农业银行-嘉实中证金融资产管理计划","group":"证金公司","num":1658600.0,"ratio":0.0787,"mv":16702102.0,"change":"不变"}]},"2017-06-30":{"mv":198181642,"num":23848573,"ratio":1.1311,"holders":[{"holder":"中央汇金资产管理有限责任公司","group":"汇金资管","num":14740600.0,"ratio":0.6991,"mv":122494386.0,"change":"不变"},{"holder":"广发基金-农业银行-广发中证金融资产管理计划","group":"证金公司","num":2738700.0,"ratio":0.1299,"mv":22758597.0,"change":"不变"},{"holder":"中国证券金融股份有限公司","group":"证金公司","num":2402973.0,"ratio":0.114,"mv":19968705.63,"change":"不变"},{"holder":"华夏基金-农业银行-华夏中证金融资产管理计划","group":"证金公司","num":2307700.0,"ratio":0.1094,"mv":19176987.0,"change":"不变"},{"holder":"嘉实基金-农业银行-嘉实中证金融资产管理计划","group":"证金公司","num":1658600.0,"ratio":0.0787,"mv":13782966.0,"change":"不变"}]},"2018-12-31":{"mv":65595670,"num":14740600,"ratio":0.6991,"holders":[{"holder":"中央汇金资产管理有限责任公司","group":"汇金资管","num":14740600.0,"ratio":0.6991,"mv":65595670.0,"change":"新进"}]},"2019-03-31":{"mv":115713710,"num":14740600,"ratio":0.6991,"holders":[{"holder":"中央汇金资产管理有限责任公司","group":"汇金资管","num":14740600.0,"ratio":0.6991,"mv":115713710.0,"change":"不变"}]},"2019-06-30":{"mv":114976680,"num":14740600,"ratio":0.6991,"holders":[{"holder":"中央汇金资产管理有限责任公司","group":"汇金资管","num":14740600.0,"ratio":0.6991,"mv":114976680.0,"change":"不变"}]},"2019-09-30":{"mv":101710140,"num":14740600,"ratio":0.7085,"holders":[{"holder":"中央汇金资产管理有限责任公司","group":"汇金资管","num":14740600.0,"ratio":0.7085,"mv":101710140.0,"change":"不变"}]},"2019-12-31":{"mv":118809236,"num":14740600,"ratio":0.7085,"holders":[{"holder":"中央汇金资产管理有限责任公司","group":"汇金资管","num":14740600.0,"ratio":0.7085,"mv":118809236.0,"change":"不变"}]},"2020-03-31":{"mv":95519088,"num":14740600,"ratio":0.7085,"holders":[{"holder":"中央汇金资产管理有限责任公司","group":"汇金资管","num":14740600.0,"ratio":0.7085,"mv":95519088.0,"change":"不变"}]},"2020-06-30":{"mv":88591006,"num":14740600,"ratio":0.7085,"holders":[{"holder":"中央汇金资产管理有限责任公司","group":"汇金资管","num":14740600.0,"ratio":0.7085,"mv":88591006.0,"change":"不变"}]},"2020-09-30":{"mv":96256118,"num":14740600,"ratio":0.7085,"holders":[{"holder":"中央汇金资产管理有限责任公司","group":"汇金资管","num":14740600.0,"ratio":0.7085,"mv":96256118.0,"change":"不变"}]}}}