{"code":"605368","name":"蓝天燃气","industry":"公用事业","industries":["公用事业","燃气Ⅱ","燃气Ⅲ"],"periods":{"2024-12-31":{"mv":117142412,"num":10248680,"ratio":1.4341,"holders":[{"holder":"中信证券股份有限公司-社保基金1106组合","group":"社保基金","num":5137760.0,"ratio":0.7189,"mv":58724596.8,"change":"新进"},{"holder":"基本养老保险基金一零零三组合","group":"养老基金","num":5110920.0,"ratio":0.7152,"mv":58417815.6,"change":"新进"}]},"2025-03-31":{"mv":115558963,"num":10759680,"ratio":1.5056,"holders":[{"holder":"基本养老保险基金一零零三组合","group":"养老基金","num":5621920.0,"ratio":0.7867,"mv":60379420.8,"change":"511000"},{"holder":"中信证券股份有限公司-社保基金1106组合","group":"社保基金","num":5137760.0,"ratio":0.7189,"mv":55179542.4,"change":"不变"}]},"2025-06-30":{"mv":110914315,"num":11271780,"ratio":1.5772,"holders":[{"holder":"基本养老保险基金一零零三组合","group":"养老基金","num":6134020.0,"ratio":0.8583,"mv":60358756.8,"change":"512100"},{"holder":"中信证券股份有限公司-社保基金1106组合","group":"社保基金","num":5137760.0,"ratio":0.7189,"mv":50555558.4,"change":"不变"}]},"2025-09-30":{"mv":110522793,"num":11465020,"ratio":1.6043,"holders":[{"holder":"基本养老保险基金一零零三组合","group":"养老基金","num":6407620.0,"ratio":0.8966,"mv":61769456.8,"change":"273600"},{"holder":"中信证券股份有限公司-社保基金1106组合","group":"社保基金","num":5057400.0,"ratio":0.7077,"mv":48753336.0,"change":"-80360"}]}}}