{"code":"834278","name":"高测股份","industry":"其他","industries":["其他"],"periods":{"2024-03-31":{"mv":79884803,"num":8426667,"ratio":2.4851,"holders":[{"holder":"广发基金管理有限公司-社保基金四二零组合","group":"社保基金","num":8426667.0,"ratio":2.4851,"mv":79884803.16,"change":"-593269"}]},"2024-06-30":{"mv":127815683,"num":13482667,"ratio":2.466,"holders":[{"holder":"广发基金管理有限公司-社保基金四二零组合","group":"社保基金","num":13482667.0,"ratio":2.466,"mv":127815683.16,"change":"5056000"}]},"2024-09-30":{"mv":111642443,"num":11776629,"ratio":2.154,"holders":[{"holder":"广发基金管理有限公司-社保基金四二零组合","group":"社保基金","num":11776629.0,"ratio":2.154,"mv":111642442.92,"change":"-1706038"}]},"2024-12-31":{"mv":118302351,"num":12479151,"ratio":2.2823,"holders":[{"holder":"广发基金管理有限公司-社保基金四二零组合","group":"社保基金","num":12479151.0,"ratio":2.2823,"mv":118302351.48,"change":"702522"}]},"2025-03-31":{"mv":99049457,"num":10448255,"ratio":1.9109,"holders":[{"holder":"广发基金管理有限公司-社保基金四二零组合","group":"社保基金","num":10448255.0,"ratio":1.9109,"mv":99049457.4,"change":"-2030896"}]},"2025-06-30":{"mv":71358131,"num":7527229,"ratio":0.9833,"holders":[{"holder":"广发基金管理有限公司-社保基金四二零组合","group":"社保基金","num":7527229.0,"ratio":0.9833,"mv":71358130.92,"change":"-2921026"}]},"2026-03-31":{"mv":92845764,"num":9793857,"ratio":1.1789,"holders":[{"holder":"全国社保基金一一五组合","group":"社保基金","num":9793857.0,"ratio":1.1789,"mv":92845764.36,"change":"新进"}]}}}